tests/__init__.py
tests/test_tce_calc.py
wet_freight_tce/__init__.py
wet_freight_tce/route_consts.py
wet_freight_tce/tce_calc.py
wet_freight_tce-1.1.1.dist-info/METADATA
wet_freight_tce-1.1.1.dist-info/WHEEL
wet_freight_tce-1.1.1.dist-info/top_level.txt
wet_freight_tce-1.1.1.dist-info/RECORD
