Metadata-Version: 2.1
Name: wet-freight-tce
Version: 1.1.1
Summary: Calculate TCE (Time Charter equivalents) for wet freight routes
Home-page: https://github.com/aeorxc/wet_freight_tce
Author: aeorxc
License: UNKNOWN
Project-URL: Source, https://github.com/aeorxc/wet_freight_tce
Platform: UNKNOWN
Classifier: Programming Language :: Python :: 3
Classifier: License :: OSI Approved :: MIT License
Classifier: Operating System :: OS Independent
Requires-Python: >=3.8
Requires-Dist: pandas
Requires-Dist: requests
